README.md
setup.py
PyFEM_TUE.egg-info/PKG-INFO
PyFEM_TUE.egg-info/SOURCES.txt
PyFEM_TUE.egg-info/dependency_links.txt
PyFEM_TUE.egg-info/requires.txt
PyFEM_TUE.egg-info/top_level.txt
pyfem/__init__.py
pyfem/elements/Composite.py
pyfem/elements/Element.py
pyfem/elements/FiniteStrainContinuum.py
pyfem/elements/Interface.py
pyfem/elements/KirchhoffBeam.py
pyfem/elements/Plate.py
pyfem/elements/SLS.py
pyfem/elements/SLSgeomdata.py
pyfem/elements/SLSkinematic.py
pyfem/elements/SLSutils.py
pyfem/elements/SmallStrainContinuum.py
pyfem/elements/SmallStrainContinuum3D.py
pyfem/elements/Spring.py
pyfem/elements/TimoshenkoBeam.py
pyfem/elements/Truss.py
pyfem/elements/__init__.py
pyfem/fem/Assembly.py
pyfem/fem/DofSpace.py
pyfem/fem/ElementSet.py
pyfem/fem/NodeSet.py
pyfem/fem/__init__.py
pyfem/io/ContourWriter.py
pyfem/io/GraphWriter.py
pyfem/io/InputReader.py
pyfem/io/MeshWriter.py
pyfem/io/OutputManager.py
pyfem/io/OutputWriter.py
pyfem/io/__init__.py
pyfem/materials/BaseMaterial.py
pyfem/materials/Dummy.py
pyfem/materials/HookesLaw.py
pyfem/materials/Isotropic.py
pyfem/materials/MaterialManager.py
pyfem/materials/MultiMaterial.py
pyfem/materials/PlaneStrain.py
pyfem/materials/PlaneStrainDamage.py
pyfem/materials/PlaneStress.py
pyfem/materials/PowerLawModeI.py
pyfem/materials/SandwichCore.py
pyfem/materials/ThoulessModeI.py
pyfem/materials/TransverseIsotropic.py
pyfem/materials/XuNeedleman.py
pyfem/materials/__init__.py
pyfem/materials/plas.py
pyfem/solvers/BuckEigSolver.py
pyfem/solvers/DissNRGSolver.py
pyfem/solvers/DissipatedEnergySolver.py
pyfem/solvers/DissipationNRGSolver.py
pyfem/solvers/DynEigSolver.py
pyfem/solvers/ExplicitSolver.py
pyfem/solvers/LinearSolver.py
pyfem/solvers/ModalSolver.py
pyfem/solvers/NonlinearSolver.py
pyfem/solvers/RiksSolver.py
pyfem/solvers/Solver.py
pyfem/solvers/__init__.py
pyfem/util/BaseModule.py
pyfem/util/BezierShapeFunctions.py
pyfem/util/__init__.py
pyfem/util/dataStructures.py
pyfem/util/fileParser.py
pyfem/util/itemList.py
pyfem/util/kinematics.py
pyfem/util/plotUtils.py
pyfem/util/shapeFunctions.py
pyfem/util/test.py
pyfem/util/transformations.py
pyfem/util/utilFunctions.py