Metadata-Version: 2.1
Name: PyFEM-TUE
Version: 3.0.2
Summary: A Python Finite Element package
Home-page: https://github.com/jjcremmers/PyFEM
Author: J.J.C. Remmers
Author-email: j.j.c.remmers@tue.nl
License: UNKNOWN
Keywords: Finite Element Method,Mechanics,Wiley
Platform: UNKNOWN
Classifier: Programming Language :: Python :: 3
Classifier: License :: OSI Approved :: GNU General Public License v3 (GPLv3)
Classifier: Operating System :: OS Independent
Requires-Python: >=3.6
